<!--   Last edited by http://encodedna.com   -->
<Library>
<List>
<code>1</code>
<BookName>Computer Architecture</BookName>
<Category>Computers</Category>
<Price>125.60</Price>
</List>
<List>
<code>2</code>
<BookName>Advanced Composite Materials</BookName>
<Category>Science</Category>
<Price>172.56</Price>
</List>
<List>
<code>3</code>
<BookName>Asp.Net 4 Blue Book</BookName>
<Category>Programming</Category>
<Price>56.00</Price>
</List>
<List>
<code>4</code>
<BookName>Stategies Unplugged</BookName>
<Category>Science</Category>
<Price>99.99</Price>
</List>
<List>
<code>5</code>
<BookName>Teaching Science</BookName>
<Category>Science</Category>
<Price>164.10</Price>
</List>
<List>
<code>6</code>
<BookName>Challenging Times</BookName>
<Category>Business</Category>
<Price>150.70</Price>
</List>
<List>
<code>7</code>
<BookName>Circuit Bending</BookName>
<Category>Science</Category>
<Price>112.00</Price>
</List>
<List>
<code>8</code>
<BookName>Popular Science</BookName>
<Category>Science</Category>
<Price>210.40</Price>
</List>
<List>
<code>9</code>
<BookName>ADOBE Premiere</BookName>
<Category>Computers</Category>
<Price>62.20</Price>
</List>
</Library>